[
    {
        "name": "Сахи",
        "position": "Младший менеджер",
        "salary": 32500.0
    },
    {
        "name": "Амир",
        "position": "Менеджер",
        "salary": 45000.0
    },
    {
        "name": "Даниял",
        "position": "Бухгалтер",
        "salary": 125000.0
    },
    {
        "name": "Алия",
        "position": "Старший менеджер",
        "salary": 75000.0
    },
    {
        "name": "Владислав",
        "position": "Консультант",
        "salary": 62500.0
    },
    {
        "name": "Ержан",
        "position": "Глав бухгалтер",
        "salary": 185000.0
    }
]